setup.py
bin/jrpc
jrpc/__init__.py
jrpc/dispatcher.py
jrpc/factory.py
jrpc/manager.py
jrpc/protocol.py
jrpc/request.py
jrpc/response.py
jrpc.egg-info/PKG-INFO
jrpc.egg-info/SOURCES.txt
jrpc.egg-info/dependency_links.txt
jrpc.egg-info/requires.txt
jrpc.egg-info/top_level.txt