Metadata-Version: 1.0
Name: jrpc
Version: 0.1.1
Summary: JSON RPC for Autobahn/Twisted
Home-page: http://github.com/dustinlacewell/jrpc
Author: Dustin Lacewell
Author-email: dlacewell@gmail.com
License: UNKNOWN
Keywords: twisted autobahn rpc json
Platform: UNKNOWN
